glasswool/__init__.py
glasswool/glasswool.py
glasswool-1.0.2.dist-info/LICENSE
glasswool-1.0.2.dist-info/METADATA
glasswool-1.0.2.dist-info/WHEEL
glasswool-1.0.2.dist-info/RECORD
