Metadata-Version: 2.1
Name: glasswool
Version: 1.0.2
Summary: Outlier filter
Author: Your Name
Author-email: you@example.com
Requires-Python: >=3.10,<3.11
Classifier: Programming Language :: Python :: 3
Classifier: Programming Language :: Python :: 3.10
Requires-Dist: conda-lock (>=1.4.0,<2.0.0)
Requires-Dist: numba (>=0.56.4,<0.57.0)
